setup.py
Yuriy1985.egg-info/PKG-INFO
Yuriy1985.egg-info/SOURCES.txt
Yuriy1985.egg-info/dependency_links.txt
Yuriy1985.egg-info/top_level.txt
project/main.py