Metadata-Version: 2.1
Name: Yuriy1985
Version: 1.0
Summary: Система аутентифікації
Author: Yuriy1985
Author-email: gward@python.net
